{"skeleton":{"hash":"pmq+fzpxrBM","spine":"4.1.19","x":-112.94,"y":-0.78,"width":251,"height":385,"images":"./images/","audio":"D:/2024/Relax Minigames/zombie"},"bones":[{"name":"root"},{"name":"zombie_head","parent":"root","x":20.29,"y":203.26},{"name":"zombie_hand_back","parent":"root","x":60.24,"y":183.29},{"name":"zombie_hand_front","parent":"root","x":4.2,"y":185.51},{"name":"zombie_leg_back","parent":"root","x":12.53,"y":129.47},{"name":"zombie_leg_front","parent":"root","x":39.16,"y":124.48}],"slots":[{"name":"zombie_leg_back","bone":"zombie_leg_back","attachment":"zombie_leg_back"},{"name":"zombie_leg_front","bone":"zombie_leg_front","attachment":"zombie_leg_front"},{"name":"zombie_hand_front","bone":"zombie_hand_front","attachment":"zombie_hand_front"},{"name":"zombie_body","bone":"root","attachment":"zombie_body"},{"name":"zombie_head","bone":"zombie_head","attachment":"zombie_head"},{"name":"zombie_hand_back","bone":"zombie_hand_back","attachment":"zombie_hand_back"}],"skins":[{"name":"default","attachments":{"zombie_body":{"zombie_body":{"x":8.56,"y":157.98,"width":123,"height":123}},"zombie_hand_back":{"zombie_hand_back":{"x":-51.18,"y":-15.07,"width":122,"height":66}},"zombie_hand_front":{"zombie_hand_front":{"x":-54.14,"y":-12.29,"width":126,"height":56}},"zombie_head":{"zombie_head":{"x":-1.23,"y":86.46,"width":238,"height":189}},"zombie_leg_back":{"zombie_leg_back":{"x":-4.47,"y":-60.25,"width":102,"height":140}},"zombie_leg_front":{"zombie_leg_front":{"x":-54.1,"y":-32.26,"width":154,"height":76}}}}],"animations":{"walk":{"slots":{"zombie_leg_back":{"rgba":[{"color":"c4c4c4ff","curve":"stepped"},{"time":0.9667,"color":"c4c4c4ff"},{"time":1,"color":"ffffffff","curve":"stepped"},{"time":1.9667,"color":"ffffffff"},{"time":2,"color":"c4c4c4ff","curve":"stepped"},{"time":2.9667,"color":"c4c4c4ff"},{"time":3,"color":"ffffffff","curve":"stepped"},{"time":3.9667,"color":"ffffffff"},{"time":4,"color":"c4c4c4ff"}]},"zombie_leg_front":{"rgba":[{"time":0.9667,"color":"ffffffff"},{"time":1,"color":"c4c4c4ff","curve":"stepped"},{"time":1.9667,"color":"c4c4c4ff"},{"time":2,"color":"ffffffff","curve":"stepped"},{"time":2.9667,"color":"ffffffff"},{"time":3,"color":"c4c4c4ff","curve":"stepped"},{"time":3.9667,"color":"c4c4c4ff"},{"time":4,"color":"ffffffff"}]}},"bones":{"zombie_leg_back":{"rotate":[{"value":7.75},{"time":0.9667,"value":7.75},{"time":1,"value":9.24},{"time":1.9667,"value":7.75,"curve":"stepped"},{"time":2,"value":7.75},{"time":2.9667,"value":7.75},{"time":3,"value":9.24},{"time":3.9667,"value":7.75}]},"root":{"rotate":[{"value":-4.84},{"time":0.8333,"value":4.01},{"time":1,"value":-4.84},{"time":1.8667,"value":4.01},{"time":2,"value":-4.84},{"time":2.8333,"value":4.01},{"time":3,"value":-4.84},{"time":3.8667,"value":4.01},{"time":4,"value":-4.84}]},"zombie_leg_front":{"rotate":[{},{"time":0.9667,"value":68.91},{"time":1},{"time":1.9667,"value":68.91},{"time":2},{"time":2.9667,"value":68.91},{"time":3},{"time":3.9667,"value":68.91},{"time":4}],"translate":[{},{"time":0.9667,"x":-42.79,"y":16.69},{"time":1},{"time":1.5,"x":-22.13,"y":15.08},{"time":1.9667,"x":-42.79,"y":16.69},{"time":2},{"time":2.9667,"x":-42.79,"y":16.69},{"time":3},{"time":3.5,"x":-22.13,"y":15.08},{"time":3.9667,"x":-42.79,"y":16.69},{"time":4}]},"zombie_hand_back":{"rotate":[{},{"time":1,"value":7.83},{"time":2},{"time":3,"value":-12.07},{"time":4}]},"zombie_hand_front":{"rotate":[{},{"time":1,"value":-10.65},{"time":2},{"time":3,"value":10.81},{"time":4}]},"zombie_head":{"rotate":[{},{"time":0.6667,"value":13.74},{"time":1,"value":-0.58},{"time":1.6667,"value":11.25},{"time":2,"value":-0.58},{"time":2.6667,"value":11.25},{"time":3,"value":-0.58},{"time":3.6667,"value":11.25},{"time":4}]}},"drawOrder":[{"time":1,"offsets":[{"slot":"zombie_leg_back","offset":1}]},{"time":2},{"time":3,"offsets":[{"slot":"zombie_leg_back","offset":1}]},{"time":4}]}}}